statzy.py
statzy-0.1.4.dist-info/licenses/LICENSE
statzy-0.1.4.dist-info/METADATA
statzy-0.1.4.dist-info/WHEEL
statzy-0.1.4.dist-info/top_level.txt
statzy-0.1.4.dist-info/RECORD
