Metadata-Version: 2.4
Name: statzy
Version: 0.1.4
Summary: Lightweight statistical utilities for data analysis and visualization
Author: aaron
Author-email: abc@example.com
Classifier: Programming Language :: Python :: 3
Classifier: License :: OSI Approved :: MIT License
Classifier: Operating System :: OS Independent
Requires-Python: >=3.6
License-File: LICENSE
Dynamic: author
Dynamic: author-email
Dynamic: classifier
Dynamic: license-file
Dynamic: requires-python
Dynamic: summary
